{
  "name": "ufront-easyauth",
  "license": "MIT",
  "classPath": "src",
  "tags": ["ufront","web","auth","neko","php","auth"],
  "description": "A basic database based user-group-permission authentication system for ufront.",
  "contributors": ["fponticelli","jason"],
  "releasenote": "Added per-user permissions. Also added ability to set current user, for 'login as' functionality.  Use with care.",
  "version": "1.0.0-beta.4",
  "url": "https://github.com/ufront/ufront-easyauth",
  "dependencies": {
    "PBKDF2": "",
    "ufront-mvc": "",
    "ufront-orm": "",
    "random": ""
  }
}
